Highton-2.0.1.dist-info/DESCRIPTION.rst
Highton-2.0.1.dist-info/METADATA
Highton-2.0.1.dist-info/RECORD
Highton-2.0.1.dist-info/WHEEL
Highton-2.0.1.dist-info/metadata.json
Highton-2.0.1.dist-info/top_level.txt
highton/__init__.py
highton/highton_constants.py
highton/highton_settings.py
highton/call_mixins/__init__.py
highton/call_mixins/call.py
highton/call_mixins/create_call_mixin.py
highton/call_mixins/create_note_call_mixin.py
highton/call_mixins/create_tag_call_mixin.py
highton/call_mixins/delete_call_mixin.py
highton/call_mixins/delete_tag_call_mixin.py
highton/call_mixins/detail_call_mixin.py
highton/call_mixins/list_call_mixin.py
highton/call_mixins/list_comment_call_mixin.py
highton/call_mixins/list_email_call_mixin.py
highton/call_mixins/list_note_call_mixin.py
highton/call_mixins/list_tag_call_mixin.py
highton/call_mixins/list_task_call_mixin.py
highton/call_mixins/search_call_mixin.py
highton/call_mixins/update_call_mixin.py
highton/fields/__init__.py
highton/fields/boolean_field.py
highton/fields/date_field.py
highton/fields/datetime_field.py
highton/fields/field.py
highton/fields/field_constants.py
highton/fields/integer_field.py
highton/fields/list_field.py
highton/fields/object_field.py
highton/fields/string_field.py
highton/models/__init__.py
highton/models/address.py
highton/models/associated_party.py
highton/models/attachment.py
highton/models/case.py
highton/models/category.py
highton/models/comment.py
highton/models/company.py
highton/models/contact.py
highton/models/contact_data.py
highton/models/deal.py
highton/models/deal_category.py
highton/models/email.py
highton/models/email_address.py
highton/models/group.py
highton/models/highton_model.py
highton/models/instant_messenger.py
highton/models/note.py
highton/models/party.py
highton/models/person.py
highton/models/phone_number.py
highton/models/status.py
highton/models/subject_data.py
highton/models/subject_field.py
highton/models/tag.py
highton/models/task.py
highton/models/task_category.py
highton/models/twitter_account.py
highton/models/type_category.py
highton/models/user.py
highton/models/web_address.py
highton/parsing/__init__.py
