Metadata-Version: 2.0
Name: Highton
Version: 2.0.1
Summary: A Python library for Highrise
Home-page: https://github.com/seibert-media/Highton
Author: Julia Giebelhausen, Jakob Löhnertz, Michael Bykovski
Author-email: brogrammers@seibert-media.net
License: Apache License 2.0
Keywords: seibertmedia seibert media python api wrapper highrise highton
Platform: UNKNOWN
Classifier: Environment :: Web Environment
Classifier: Framework :: Django
Classifier: Intended Audience :: Developers
Classifier: License :: OSI Approved :: Apache Software License
Classifier: Operating System :: OS Independent
Classifier: Programming Language :: Python
Classifier: Programming Language :: Python :: 2
Classifier: Programming Language :: Python :: 2.6
Classifier: Programming Language :: Python :: 2.7
Classifier: Programming Language :: Python :: 3
Classifier: Programming Language :: Python :: 3.2
Classifier: Programming Language :: Python :: 3.3
Classifier: Programming Language :: Python :: 3.4
Classifier: Topic :: Internet :: WWW/HTTP
Requires-Dist: requests
